atomictrust_tpf/__init__.py
atomictrust_tpf/flashapce.py
atomictrust_tpf/py.typed
atomictrust_tpf/router.py
atomictrust_tpf-1.0.1.dist-info/licenses/LICENSE
atomictrust_tpf-1.0.1.dist-info/METADATA
atomictrust_tpf-1.0.1.dist-info/WHEEL
atomictrust_tpf-1.0.1.dist-info/top_level.txt
atomictrust_tpf-1.0.1.dist-info/RECORD
