Metadata-Version: 2.4
Name: atomictrust-tpf
Version: 1.0.1
Summary: Free uncertainty quantification for diffusion language models
Author-email: Rafael Velado <licensing@atomic-trust.com>
Maintainer-email: Rafael Velado <licensing@atomic-trust.com>
License: Apache-2.0
Project-URL: Homepage, https://github.com/atomictrust/tpf-confidence
Project-URL: Documentation, https://github.com/atomictrust/tpf-confidence#readme
Project-URL: Repository, https://github.com/atomictrust/tpf-confidence
Project-URL: Paper, https://doi.org/10.5281/zenodo.18111467
Project-URL: LinkedIn, https://linkedin.com/in/rafael-velado-cissp-77337b30
Keywords: diffusion,llm,uncertainty,confidence,tpf,tokens-per-forward,hallucination-detection,ai-safety,attention-verification,flashattention
Classifier: Development Status :: 4 - Beta
Classifier: Intended Audience :: Developers
Classifier: Intended Audience :: Science/Research
Classifier: License :: OSI Approved :: Apache Software License
Classifier: Operating System :: OS Independent
Classifier: Programming Language :: Python :: 3
Classifier: Programming Language :: Python :: 3.10
Classifier: Programming Language :: Python :: 3.11
Classifier: Programming Language :: Python :: 3.12
Classifier: Topic :: Scientific/Engineering :: Artificial Intelligence
Classifier: Topic :: Security :: Cryptography
Classifier: Typing :: Typed
Requires-Python: >=3.10
License-File: LICENSE
Requires-Dist: numpy>=1.24.0
Requires-Dist: blake3>=0.3.0
Provides-Extra: gpu
Requires-Dist: torch>=2.1.0; extra == "gpu"
Requires-Dist: triton>=2.1.0; extra == "gpu"
Provides-Extra: full
Requires-Dist: torch>=2.1.0; extra == "full"
Requires-Dist: triton>=2.1.0; extra == "full"
Requires-Dist: vllm>=0.3.0; extra == "full"
Requires-Dist: transformers>=4.36.0; extra == "full"
Requires-Dist: accelerate>=0.25.0; extra == "full"
Requires-Dist: sentence-transformers>=2.2.0; extra == "full"
Provides-Extra: dev
Requires-Dist: pytest>=7.0.0; extra == "dev"
Requires-Dist: pytest-cov>=4.0.0; extra == "dev"
Requires-Dist: black>=23.0.0; extra == "dev"
Requires-Dist: ruff>=0.1.0; extra == "dev"
Requires-Dist: isort>=5.12.0; extra == "dev"
Requires-Dist: mypy>=1.0.0; extra == "dev"
Dynamic: license-file
